Modeva-1.0.15.dist-info/RECORD
Modeva-1.0.15.dist-info/top_level.txt
Modeva-1.0.15.dist-info/WHEEL
Modeva-1.0.15.dist-info/METADATA
modeva/exceptions.cpython-310-x86_64-linux-gnu.so
modeva/__init__.py
modeva/auth.cpython-310-x86_64-linux-gnu.so
modeva/testsuite/base.cpython-310-x86_64-linux-gnu.so
modeva/testsuite/local_testsuite.cpython-310-x86_64-linux-gnu.so
modeva/testsuite/__init__.py
modeva/testsuite/explain/lime.cpython-310-x86_64-linux-gnu.so
modeva/testsuite/explain/ale.cpython-310-x86_64-linux-gnu.so
modeva/testsuite/explain/base.cpython-310-x86_64-linux-gnu.so
modeva/testsuite/explain/shap.cpython-310-x86_64-linux-gnu.so
modeva/testsuite/explain/__init__.py
modeva/testsuite/explain/pdp.cpython-310-x86_64-linux-gnu.so
modeva/testsuite/explain/hstatistic.cpython-310-x86_64-linux-gnu.so
modeva/testsuite/explain/pfi.cpython-310-x86_64-linux-gnu.so
modeva/testsuite/explain/PyALE/_ALE_generic.cpython-310-x86_64-linux-gnu.so
modeva/testsuite/explain/PyALE/__init__.py
modeva/testsuite/explain/PyALE/_src/ALE_2D.cpython-310-x86_64-linux-gnu.so
modeva/testsuite/explain/PyALE/_src/lib.cpython-310-x86_64-linux-gnu.so
modeva/testsuite/explain/PyALE/_src/ALE_1D.cpython-310-x86_64-linux-gnu.so
modeva/testsuite/explain/PyALE/_src/__init__.py
modeva/testsuite/diagnose/residual_interpret.cpython-310-x86_64-linux-gnu.so
modeva/testsuite/diagnose/mitigate_unfair_binning.cpython-310-x86_64-linux-gnu.so
modeva/testsuite/diagnose/slicing_robustness.cpython-310-x86_64-linux-gnu.so
modeva/testsuite/diagnose/base.cpython-310-x86_64-linux-gnu.so
modeva/testsuite/diagnose/slicing_fairness.cpython-310-x86_64-linux-gnu.so
modeva/testsuite/diagnose/mitigate_unfair_thresholding.cpython-310-x86_64-linux-gnu.so
modeva/testsuite/diagnose/slicing_reliability.cpython-310-x86_64-linux-gnu.so
modeva/testsuite/diagnose/robustness.cpython-310-x86_64-linux-gnu.so
modeva/testsuite/diagnose/residual.cpython-310-x86_64-linux-gnu.so
modeva/testsuite/diagnose/resilience.cpython-310-x86_64-linux-gnu.so
modeva/testsuite/diagnose/reliability.cpython-310-x86_64-linux-gnu.so
