Metadata-Version: 2.1
Name: Modeva
Version: 1.0.15
Summary: Integrated tool for model development and validation.
Author-email: admin@modeva.ai
License: proprietary
Classifier: Programming Language :: Python :: 3.9
Classifier: Programming Language :: Python :: 3.10
Classifier: Programming Language :: Python :: 3.11
Classifier: Programming Language :: Python :: 3.12
Requires-Dist: mlflow ==2.15.1
Requires-Dist: supabase
Requires-Dist: ipywidgets >=7.7.0
Requires-Dist: ipython >=7.12.0
Requires-Dist: ipyvuetify >=1.8.10
Requires-Dist: notebook >=7.0.0
Requires-Dist: mocharts >=1.0.3
Requires-Dist: numpy <=1.26.4,>=1.21.4
Requires-Dist: scipy >=1.5.3
Requires-Dist: pandas >=1.3.5
Requires-Dist: catboost
Requires-Dist: xgboost >=1.6.0
Requires-Dist: lightgbm >=3.3.2
Requires-Dist: scikit-learn <1.7.0,>=1.3.0
Requires-Dist: scikit-learn-extra
Requires-Dist: torch !=2.3.*,>=1.11.0
Requires-Dist: momentchi2
Requires-Dist: umap-learn
Requires-Dist: pyswarms
Requires-Dist: lime >=0.2.0.1
Requires-Dist: shap >=0.42.0
Requires-Dist: tqdm
Requires-Dist: dill
Requires-Dist: httpx
Requires-Dist: python-dateutil
